[
  {
    "id": "I2",
    "scoreHome": 4,
    "scoreAway": 1,
    "goalsHome": [
      { "player": "Erling Haaland", "minute": "29'" },
      { "player": "Erling Haaland", "minute": "43'" },
      { "player": "Leo Østigård", "minute": "76'" },
      { "player": "Aymen Hussein (g.c.)", "minute": "90+6'" }
    ],
    "goalsAway": [
      { "player": "Aymen Hussein", "minute": "39'" }
    ],
    "cardsHome": [],
    "cardsAway": []
  },
  {
    "id": "J1",
    "scoreHome": 3,
    "scoreAway": 0,
    "goalsHome": [
      { "player": "Lionel Messi", "minute": "17'" },
      { "player": "Lionel Messi", "minute": "60'" },
      { "player": "Lionel Messi", "minute": "76'" }
    ],
    "goalsAway": [],
    "cardsHome": [],
    "cardsAway": []
  }
]
